is_numeric/__init__.py
is_numeric/test_is_numeric.py
is_numeric-1.0.1.dist-info/LICENSE
is_numeric-1.0.1.dist-info/METADATA
is_numeric-1.0.1.dist-info/WHEEL
is_numeric-1.0.1.dist-info/top_level.txt
is_numeric-1.0.1.dist-info/RECORD
