Metadata-Version: 2.1
Name: is-numeric
Version: 1.0.1
Summary: The missing Python method to determine if a value is numeric
Author: Mighty Pulpo
Author-email: jayray.net@gmail.com
Keywords: isnumeric,is_numeric,number,isnumber,is_number,"is numeric","is number",numeric
Classifier: Programming Language :: Python :: 3
Classifier: License :: OSI Approved :: MIT License
Classifier: Operating System :: OS Independent
Requires-Python: >=3.6
License-File: LICENSE
